hipchat/__init__.py
hipchat/compat.py
hipchat/exceptions.py
hipchat/logger.py
hipchat/notifications.py
hipchat/tests.py
hipchat_notifications-0.4.1.dist-info/DESCRIPTION.rst
hipchat_notifications-0.4.1.dist-info/METADATA
hipchat_notifications-0.4.1.dist-info/RECORD
hipchat_notifications-0.4.1.dist-info/WHEEL
hipchat_notifications-0.4.1.dist-info/metadata.json
hipchat_notifications-0.4.1.dist-info/top_level.txt
