Metadata-Version: 2.0
Name: hipchat-notifications
Version: 0.4.1
Summary: Basic functions for sending notifications via HipChat API (v2)
Home-page: https://github.com/yunojuno/hipchat-notifications
Author: YunoJuno
Author-email: code@yunojuno.com
License: MIT
Platform: UNKNOWN
Classifier: Intended Audience :: Developers
Classifier: License :: OSI Approved :: MIT License
Classifier: Operating System :: OS Independent
Classifier: Programming Language :: Python
Classifier: Programming Language :: Python :: 2.7
Classifier: Programming Language :: Python :: 3.6
Requires-Dist: requests (>=2.1)
